odoo/addons/edi_sale_endpoint/README.rst
odoo/addons/edi_sale_endpoint/__init__.py
odoo/addons/edi_sale_endpoint/__manifest__.py
odoo/addons/edi_sale_endpoint/i18n/edi_sale_endpoint.pot
odoo/addons/edi_sale_endpoint/i18n/it.po
odoo/addons/edi_sale_endpoint/readme/CONTRIBUTORS.md
odoo/addons/edi_sale_endpoint/readme/DESCRIPTION.md
odoo/addons/edi_sale_endpoint/static/description/icon.png
odoo/addons/edi_sale_endpoint/static/description/index.html
odoo/addons/edi_sale_endpoint/views/sale_order.xml
odoo_addon_edi_sale_endpoint-18.0.1.0.0.2.dist-info/METADATA
odoo_addon_edi_sale_endpoint-18.0.1.0.0.2.dist-info/WHEEL
odoo_addon_edi_sale_endpoint-18.0.1.0.0.2.dist-info/top_level.txt
odoo_addon_edi_sale_endpoint-18.0.1.0.0.2.dist-info/RECORD
