Metadata-Version: 2.1
Name: odoo-addon-edi_sale_endpoint
Version: 18.0.1.0.0.2
Requires-Python: >=3.10
Requires-Dist: odoo-addon-edi_endpoint_oca==18.0.*
Requires-Dist: odoo-addon-edi_sale_oca==18.0.*
Requires-Dist: odoo==18.0.*
Summary: Glue module between edi_sale_oca and edi_endpoint_oca.
Home-page: https://github.com/OCA/edi-framework
License: AGPL-3
Author: Camptocamp,Odoo Community Association (OCA)
Author-email: support@odoo-community.org
Classifier: Programming Language :: Python
Classifier: Framework :: Odoo
Classifier: Framework :: Odoo :: 18.0
Classifier: License :: OSI Approved :: GNU Affero General Public License v3
Classifier: Development Status :: 3 - Alpha
